angel/__init__.py
angel/tryout.py
angel_tag-0.0.6.dist-info/LICENSE.txt
angel_tag-0.0.6.dist-info/METADATA
angel_tag-0.0.6.dist-info/WHEEL
angel_tag-0.0.6.dist-info/top_level.txt
angel_tag-0.0.6.dist-info/RECORD
