Metadata-Version: 2.1
Name: angel-tag
Version: 0.0.6
Summary: An Ancient Greek Morphology Tagger
Home-page: https://chrisdrymon.com
Author: Chris Drymon
Author-email: chrisdrymon@yahoo.com
License: MIT
Keywords: greek,ancient greek,morphology,classics,computational linguistics
Platform: UNKNOWN
Classifier: Development Status :: 2 - Pre-Alpha
Classifier: Intended Audience :: Developers
Classifier: Intended Audience :: Education
Classifier: Intended Audience :: Religion
Classifier: License :: OSI Approved :: MIT License
Classifier: Natural Language :: Greek
Classifier: Natural Language :: English
Classifier: Operating System :: Microsoft :: Windows :: Windows 10
Classifier: Operating System :: MacOS :: MacOS X
Classifier: Programming Language :: Python :: 3 :: Only
Classifier: Programming Language :: Python :: 3.7
Classifier: Programming Language :: Python :: 3.8
Classifier: Topic :: Text Processing :: Linguistic
Requires-Python: ==3.7.*, ==3.8.*
Requires-Dist: tensorflow
Requires-Dist: numpy
Requires-Dist: gdown
Requires-Dist: greek-normalisation
Requires-Dist: gensim
